{
  "updatedAt": "2026-07-20T00:00:15.758Z",
  "timezone": "America/Toronto",
  "stations": {
    "chyz": {
      "id": "chyz",
      "name": "CHYZ 94,3",
      "current": {
        "title": "Capitales de Québec",
        "source": "schedule",
        "start": "16:50",
        "end": "20:30",
        "url": "https://chyz.ca/emission/capitales-de-quebec/"
      },
      "next": {
        "title": "Lundi Indie",
        "source": "schedule",
        "start": "08:00",
        "end": "10:00",
        "url": "https://chyz.ca/emission/lundie-indie-playlist-du-matin/"
      },
      "track": "",
      "showTitle": "Capitales de Québec",
      "host": "",
      "source": "schedule",
      "sources": [
        "schedule"
      ],
      "clientPoll": null,
      "checkedAt": "2026-07-19T23:59:53.665Z"
    },
    "cism": {
      "id": "cism",
      "name": "CISM 89,3",
      "current": {
        "title": "Le char de marge",
        "source": "api-live",
        "start": "14:00",
        "url": "https://stream03.ustream.ca/cism128.mp3",
        "slug": "le-char-de-marge"
      },
      "next": {
        "title": "Vibrance",
        "source": "api-live",
        "start": "16:00",
        "url": "https://podcast.cism893.ca/podcast/download_mp3/364257.mp3",
        "slug": "vibrance"
      },
      "track": "",
      "showTitle": "Le char de marge",
      "host": "",
      "source": "api-live",
      "sources": [
        "api-live"
      ],
      "clientPoll": {
        "type": "cism-v1",
        "url": "https://admin.cism893.ca/api/v1/live"
      },
      "checkedAt": "2026-07-19T23:59:55.383Z"
    },
    "ckut": {
      "id": "ckut",
      "name": "CKUT 90,3",
      "current": {
        "title": "Bluegrass Rambling",
        "source": "api-live",
        "start": "19:00",
        "end": "20:00"
      },
      "next": {
        "title": "Country Classics",
        "source": "api-live",
        "start": "20:00",
        "end": "21:00"
      },
      "track": "",
      "showTitle": "Bluegrass Rambling",
      "host": "",
      "source": "api-live",
      "sources": [
        "api-live",
        "stream"
      ],
      "clientPoll": null,
      "checkedAt": "2026-07-19T23:59:58.601Z"
    },
    "cjlo": {
      "id": "cjlo",
      "name": "CJLO 1690AM",
      "current": {
        "title": "Eastern ...",
        "source": "schedule",
        "start": "20:00",
        "end": "20:30",
        "url": "http://www.cjlo.com/shows/eastern-promises"
      },
      "next": {
        "title": "Afro Archives",
        "source": "schedule",
        "start": "21:00",
        "end": "22:00",
        "url": "http://www.cjlo.com/shows/afro-archives"
      },
      "track": "",
      "showTitle": "Eastern ...",
      "host": "",
      "source": "schedule",
      "sources": [
        "schedule"
      ],
      "clientPoll": null,
      "checkedAt": "2026-07-20T00:00:12.426Z"
    },
    "cfak": {
      "id": "cfak",
      "name": "CFAK 88,3",
      "current": {
        "title": "Les nuits CFAK",
        "source": "schedule",
        "start": "00:00",
        "end": "21:00"
      },
      "next": {
        "title": "Solénoïde",
        "source": "schedule",
        "start": "21:00",
        "end": "00:00"
      },
      "track": "",
      "showTitle": "Les nuits CFAK",
      "host": "",
      "source": "schedule",
      "sources": [
        "schedule"
      ],
      "clientPoll": null,
      "checkedAt": "2026-07-20T00:00:13.033Z"
    },
    "choq": {
      "id": "choq",
      "name": "CHOQ.ca",
      "current": {
        "title": "PromoRadioFlIM2026",
        "source": "api-live"
      },
      "next": null,
      "track": "Laura Schembri - Sur le dos de ta moto",
      "showTitle": "PromoRadioFlIM2026",
      "host": "",
      "source": "api-live",
      "sources": [
        "api-live",
        "stream"
      ],
      "clientPoll": null,
      "checkedAt": "2026-07-20T00:00:15.407Z"
    }
  }
}
